chuk_lazarus/__init__.py
chuk_lazarus/cli/__init__.py
chuk_lazarus/cli/main.py
chuk_lazarus/configs/finetune/calvin-granite-3b-config.yaml
chuk_lazarus/configs/finetune/calvin-mistral-7b-config.yaml
chuk_lazarus/configs/finetune/calvin-tinyllama-3b-config.yaml
chuk_lazarus/configs/pretrain/granite-3b-phase-1.yaml
chuk_lazarus/configs/pretrain/granite-3b-phase-2.yaml
chuk_lazarus/configs/pretrain/lazyfox.yaml
chuk_lazarus/configs/pretrain/tiny_shakespeare.yaml
chuk_lazarus/configs/sft/granite-3b.yaml
chuk_lazarus/data/__init__.py
chuk_lazarus/data/base_dataset.py
chuk_lazarus/data/batch_dataset_base.py
chuk_lazarus/data/classification_dataset.py
chuk_lazarus/data/preference_dataset.py
chuk_lazarus/data/protocols.py
chuk_lazarus/data/rollout_buffer.py
chuk_lazarus/data/sft_dataset.py
chuk_lazarus/data/train_batch_dataset.py
chuk_lazarus/data/batching/README.md
chuk_lazarus/data/batching/__init__.py
chuk_lazarus/data/batching/analyze/__init__.py
chuk_lazarus/data/batching/analyze/efficiency.py
chuk_lazarus/data/batching/core/__init__.py
chuk_lazarus/data/batching/core/buckets.py
chuk_lazarus/data/batching/core/metrics.py
chuk_lazarus/data/batching/core/sampler.py
chuk_lazarus/data/batching/generation/__init__.py
chuk_lazarus/data/batching/generation/io.py
chuk_lazarus/data/batching/generation/length_cache.py
chuk_lazarus/data/batching/planning/__init__.py
chuk_lazarus/data/batching/planning/batch_plan.py
chuk_lazarus/data/batching/planning/packing.py
chuk_lazarus/data/batching/planning/predictability.py
chuk_lazarus/data/batching/streaming/__init__.py
chuk_lazarus/data/batching/streaming/gym_stream.py
chuk_lazarus/data/batching/streaming/offline_stream.py
chuk_lazarus/data/batching/streaming/protocols.py
chuk_lazarus/data/batching/streaming/replay_buffer.py
chuk_lazarus/data/batching/streaming/rolling_window.py
chuk_lazarus/data/batching/streaming/telnet_client.py
chuk_lazarus/data/batching/streaming/types.py
chuk_lazarus/data/generators/__init__.py
chuk_lazarus-0.4.dist-info/METADATA
chuk_lazarus-0.4.dist-info/WHEEL
chuk_lazarus-0.4.dist-info/entry_points.txt
chuk_lazarus-0.4.dist-info/RECORD
