Metadata-Version: 2.4
Name: chuk-lazarus
Version: 0.4
Summary: MLX-based LLM training and inference with hybrid RL architecture
Requires-Python: >=3.10
Requires-Dist: aiofiles>=23.0.0
Requires-Dist: huggingface-hub<0.24.0,>=0.23.0
Requires-Dist: mlx-lm>=0.12.0
Requires-Dist: mlx>=0.12.0
Requires-Dist: numpy>=1.24.0
Requires-Dist: pydantic>=2.0.0
Requires-Dist: pyyaml>=6.0
Requires-Dist: tabulate>=0.9.0
Requires-Dist: tqdm>=4.65.0
Requires-Dist: transformers>=4.40.1
Requires-Dist: typer>=0.9.0
Provides-Extra: dev
Requires-Dist: bandit>=1.7.0; extra == 'dev'
Requires-Dist: build>=1.0.0; extra == 'dev'
Requires-Dist: mypy>=1.0.0; extra == 'dev'
Requires-Dist: pytest-asyncio>=0.23.0; extra == 'dev'
Requires-Dist: pytest-cov>=4.0.0; extra == 'dev'
Requires-Dist: pytest-watch>=4.2.0; extra == 'dev'
Requires-Dist: pytest>=7.0.0; extra == 'dev'
Requires-Dist: ruff>=0.1.0; extra == 'dev'
Requires-Dist: torch>=2.0.0; extra == 'dev'
Requires-Dist: twine>=4.0.0; extra == 'dev'
Requires-Dist: types-aiofiles>=23.0.0; extra == 'dev'
Requires-Dist: types-pyyaml>=6.0.0; extra == 'dev'
Requires-Dist: types-tabulate>=0.9.0; extra == 'dev'
Provides-Extra: fast
Requires-Dist: mlx-data>=0.0.3; extra == 'fast'
Provides-Extra: openai
Requires-Dist: tiktoken>=0.5.0; extra == 'openai'
